[
    {
        "path": "Pictures/Camera Roll/desktop.ini",
        "checksum": "/OHmV1YTijyk6q+PdkKGcgW0SJc="
    },
    {
        "path": "NTUSER_D.REG",
        "checksum": "qCg7n8/YkAeHEtHjhP0nL3QqxDk="
    },
    {
        "path": "Pictures/desktop.ini",
        "checksum": "1izMgwwknea2UyOBtMFqXxf5XYk="
    },
    {
        "path": "3D Objects/desktop.ini",
        "checksum": "PclXWnLqiWo6kQr49OQ8kpOaRCE="
    },
    {
        "path": "Desktop/__TORREN.LNK",
        "checksum": "+r9ZOIopIdl/XpdChanVTdOh8QI="
    },
    {
        "path": "DOWNLOAD/UTORRENT.EXE",
        "checksum": "Ue4ekkS7gQQ9Ep5zAdAWu8POqD0="
    },
    {
        "path": "_BASH_HI",
        "checksum": "ZjYJdpCAR4BlqlyMx9hcrpAMwfw="
    },
    {
        "path": "Links/Desktop.lnk",
        "checksum": "N5bnlqTO30gqDPxrj5dncDLS6/Y="
    },
    {
        "path": "NTUSE000.REG",
        "checksum": "alIeHSpjLCblO4PSzEsO3s/B5ow="
    },
    {
        "path": "Pictures/Saved Pictures/desktop.ini",
        "checksum": "4FCMPxSWBzufb57LL7AcuR+eggE="
    },
    {
        "path": "DOWNLOAD/FIREFOX_.EXE",
        "checksum": "3BsbiKl6Fm5sxvn8Y+MDn2IfQcs="
    },
    {
        "path": "ntuser.ini",
        "checksum": "eJTsAWUf8/zfnRF/QWh1u67wO20="
    },
    {
        "path": "NTUSER.DAT{1c3790b4-b8ad-11e8-aa21-e41d2d101530}.TMContainer00000000000000000001.regtrans-ms",
        "checksum": "5PoA+msrwuP6rrzeWkcFL1LVQ4c="
    },
    {
        "path": "Links/DOWNLOAD.LNK",
        "checksum": "CZIAbA9M+R22UhFEyaueus1ezZI="
    },
    {
        "path": "OneDrive/desktop.ini",
        "checksum": "E9yo0U0vNDyMrrRPd37nehUYUP8="
    },
    {
        "path": "NTUSER.DAT{1c3790b4-b8ad-11e8-aa21-e41d2d101530}.TM.blf",
        "checksum": "h7IgaWmKb6zrwkrr4oShILV8EI0="
    },
    {
        "path": "NTUSER.DAT{1c3790b4-b8ad-11e8-aa21-e41d2d101530}.TMContainer00000000000000000002.regtrans-ms",
        "checksum": "alIeHSpjLCblO4PSzEsO3s/B5ow="
    },
    {
        "path": "Searches/Indexed Locations.search-ms",
        "checksum": "SQXwLb72nIMLgHoy6aS2IGvQHcY="
    },
    {
        "path": "Music/FILE_EXA.MP3",
        "checksum": "2ulNKuQZs5jJd/J/QZBoBxWuEMM="
    },
    {
        "path": "MicrosoftEdgeBackups/backups/MicrosoftEdgeBackup20240204/MicrosoftEdgeCookiesBackup.dat",
        "checksum": "aulTPYXY8QRaaHJQHhAuw36RkzI="
    },
    {
        "path": "FAVORITE/DESKTOP.INI",
        "checksum": "WzFyU6Y/7LFnvwe++gXF7QnEzOo="
    },
    {
        "path": "_SSH/ENVIRONM",
        "checksum": "3KubBYOR346il0hQEOwym/YNioU="
    },
    {
        "path": "MicrosoftEdgeBackups/backups/MicrosoftEdgeBackup20240204/DatastoreBackup/edb00001.log",
        "checksum": "XVtHRFiuzXr9uiPpTpXk0ObXquo="
    },
    {
        "path": "DOWNLOAD/NPP_7_9_.EXE",
        "checksum": "ZJ83OcIMssrMigjbwnZ5O+1F/E4="
    },
    {
        "path": "Searches/INDEXED_.SEA",
        "checksum": "SQXwLb72nIMLgHoy6aS2IGvQHcY="
    },
    {
        "path": "Searches/EVERYWHE.SEA",
        "checksum": "2QTWaDpUiwOVDZTaM838y7Vam8c="
    },
    {
        "path": "Searches/desktop.ini",
        "checksum": "iPHGRzeLWyLrrbRl3ID8/Z57l8k="
    },
    {
        "path": "Music/desktop.ini",
        "checksum": "iDrlJ+6D7ZNGzYLDPfwOuXKY3BQ="
    },
    {
        "path": "Links/Downloads.lnk",
        "checksum": "LmEfTRGMCXapw5x/0jlbV/z4O/o="
    },
    {
        "path": "Desktop/desktop.ini",
        "checksum": "dyb1UBLh4mzHYsmYLnxsVMp7swM="
    },
    {
        "path": "MicrosoftEdgeBackups/backups/MicrosoftEdgeBackup20240204/MicrosoftEdgeSettingsBackup.txt",
        "checksum": "4kMWXCW8aZTbff0xGW/YwlByNaQ="
    },
    {
        "path": "DOCUMENT/DESKTOP.INI",
        "checksum": "9ygHqeCBkGZUrhlmBeaB1ZOKLmw="
    },
    {
        "path": "Documents/desktop.ini",
        "checksum": "9ygHqeCBkGZUrhlmBeaB1ZOKLmw="
    },
    {
        "path": ".vbox_version.lockbit",
        "checksum": "UMYAe7abIwgGYHjcgHoIVZlhdKc="
    },
    {
        "path": "Searches/Everywhere.search-ms",
        "checksum": "2QTWaDpUiwOVDZTaM838y7Vam8c="
    },
    {
        "path": "Searches/winrt--{S-1-5-21-3461203602-4096304019-2269080069-1000}-.searchconnector-ms",
        "checksum": "RE3ojte/TbfGPFKSBDUUA1wWb3Q="
    },
    {
        "path": "Links/desktop.ini",
        "checksum": "Conoe6RlOMtzr/Gkfk3AvPtHYNU="
    },
    {
        "path": "Desktop/eula.lnk",
        "checksum": "IXaJHzBzxmj374ei/oLi6tWILrs="
    },
    {
        "path": "Desktop/OPERA_BR.LNK",
        "checksum": "tMlStrwh1cEi/DAKtQ6JlwcTcS8="
    },
    {
        "path": "Favorites/desktop.ini",
        "checksum": "WzFyU6Y/7LFnvwe++gXF7QnEzOo="
    },
    {
        "path": "Downloads/desktop.ini",
        "checksum": "MM7ZJ+I7WEclzxY1E5QXWm0qlXc="
    },
    {
        "path": "FAVORITE/LINKS_FO/DESKTOP.INI",
        "checksum": "G15uwyQV0BDlMRyuox35awKU+2U="
    },
    {
        "path": "SAVED_GA/DESKTOP.INI",
        "checksum": "PacqUuRRomypo1YR+ocWBEp8C7w="
    },
    {
        "path": "Contacts/desktop.ini",
        "checksum": "oxajjhqDJb729o8YvJZ7mqqLbr0="
    },
    {
        "path": "init.bat",
        "checksum": "tpDuu5nJtPkO+fGqVdXe51tEMSM="
    },
    {
        "path": "Links/RECENTPL.LNK",
        "checksum": "Ad1P2yYPZpIwBKy1qHQRGp0U2jg="
    },
    {
        "path": "Music/FILE_002.MP3",
        "checksum": "WK8jYkSpUErL1KsHw9n9l4HSVAI="
    },
    {
        "path": "MicrosoftEdgeBackups/backups/MicrosoftEdgeBackup20240204/DatastoreBackup/spartan.edb",
        "checksum": "XxvBIzJZKkVpOzFVARU/dJR42n0="
    },
    {
        "path": "MicrosoftEdgeBackups/backups/MicrosoftEdgeBackup20240204/DatastoreBackup/spartan.pat",
        "checksum": "2jmj7l5rSw0yVb/vlWAYkK/YBwk="
    },
    {
        "path": "MicrosoftEdgeBackups/backups/MicrosoftEdgeBackup20240204/Protected - It is a violation of Windows Policy to modify/Backup.dat",
        "checksum": "F1t9hXQ/5l1hLjm09MlO0EfXhHA="
    },
    {
        "path": "DOWNLOAD/SKYPE_8_.EXE",
        "checksum": "2ujxf4oqBOZigUL5WRLNdhKigpI="
    },
    {
        "path": "Music/FILE_001.MP3",
        "checksum": "0nrSVZOsNRVIbbF2XgWj1VywuXk="
    },
    {
        "path": "FAVORITE/LINKS/DESKTOP.INI",
        "checksum": "I0XMd1dvZmuBK1XqdCC40sTSoLU="
    },
    {
        "path": "MicrosoftEdgeBackups/backups/MicrosoftEdgeBackup20240204/DatastoreBackup/schema.txt",
        "checksum": "rRLfF9CbAk3IgTCr16K0cOeRhY8="
    },
    {
        "path": "Favorites/Links/desktop.ini",
        "checksum": "I0XMd1dvZmuBK1XqdCC40sTSoLU="
    },
    {
        "path": "NTUSER_D.BLF",
        "checksum": "9ziWAIBdhEONgUvQA0xrhk6OqnU="
    },
    {
        "path": "Music/FILE_000.MP3",
        "checksum": "BRoAdwGuUZIeLl7sGd/v1ZWswjg="
    },
    {
        "path": "DOWNLOAD/DESKTOP.INI",
        "checksum": "MM7ZJ+I7WEclzxY1E5QXWm0qlXc="
    },
    {
        "path": "Videos/Captures/desktop.ini",
        "checksum": "YiZPi1wvUDSh5BQ99ujHhxZfvC8="
    },
    {
        "path": "Saved Games/desktop.ini",
        "checksum": "PacqUuRRomypo1YR+ocWBEp8C7w="
    },
    {
        "path": "Videos/desktop.ini",
        "checksum": "ELzn6kUHfAuqsFXgYC7veH26c14="
    }
]